paperctl/__init__.py
paperctl/__main__.py
paperctl/cli/__init__.py
paperctl/cli/archives.py
paperctl/cli/config.py
paperctl/cli/groups.py
paperctl/cli/main.py
paperctl/cli/pull.py
paperctl/cli/search.py
paperctl/cli/systems.py
paperctl/client/__init__.py
paperctl/client/api.py
paperctl/client/async_api.py
paperctl/client/exceptions.py
paperctl/client/models.py
paperctl/config/__init__.py
paperctl/config/settings.py
paperctl/formatters/__init__.py
paperctl/formatters/csv.py
paperctl/formatters/json.py
paperctl/formatters/text.py
paperctl/utils/__init__.py
paperctl/utils/rate_limiter.py
paperctl/utils/retry.py
paperctl/utils/time.py
paperctl-1.2.0.dist-info/WHEEL
paperctl-1.2.0.dist-info/entry_points.txt
paperctl-1.2.0.dist-info/METADATA
paperctl-1.2.0.dist-info/RECORD
