Metadata-Version: 2.3
Name: paperctl
Version: 1.2.0
Summary: Modern CLI tool for querying Papertrail logs
Keywords: papertrail,logs,cli,logging
Author: Jonathan Moss
Author-email: Jonathan Moss <jmoss@mozilla.com>
License: MPL-2.0
Classifier: Development Status :: 4 - Beta
Classifier: Intended Audience :: Developers
Classifier: License :: OSI Approved :: Mozilla Public License 2.0 (MPL 2.0)
Classifier: Programming Language :: Python :: 3
Classifier: Programming Language :: Python :: 3.11
Classifier: Programming Language :: Python :: 3.12
Classifier: Programming Language :: Python :: 3.13
Classifier: Programming Language :: Python :: 3.14
Classifier: Topic :: System :: Logging
Classifier: Topic :: Utilities
Requires-Dist: httpx>=0.28.1
Requires-Dist: pydantic>=2.12.5
Requires-Dist: pydantic-settings>=2.12.0
Requires-Dist: python-dateutil>=2.9.0.post0
Requires-Dist: rich>=14.3.1
Requires-Dist: typer>=0.21.1
Requires-Python: >=3.11
Project-URL: Homepage, https://github.com/jwmossmoz/paperctl
Project-URL: Repository, https://github.com/jwmossmoz/paperctl
Project-URL: Issues, https://github.com/jwmossmoz/paperctl/issues
